{
  "nodes": {
    "root_nodes": [
      {
        "id": "Root_01",
        "semantic_name": "应用程序入口",
        "description": "包含程序入口点 main 函数，负责初始化并驱动调度器"
      },
      {
        "id": "Root_02",
        "semantic_name": "模型层",
        "description": "定义核心业务实体 Task，包含任务ID、优先级和激活状态"
      },
      {
        "id": "Root_03",
        "semantic_name": "核心调度层",
        "description": "实现任务调度器 Scheduler，包含优先级计数和任务评估逻辑"
      }
    ],
    "intermediate_nodes": [
      {
        "id": "Intermediate_main_cpp",
        "parent_root": "Root_01",
        "file_path": "src/main.cpp",
        "semantic_name": "主程序源文件",
        "description": "程序入口点，创建任务和调度器并执行评估"
      },
      {
        "id": "Intermediate_task_hpp",
        "parent_root": "Root_02",
        "file_path": "src/models/task.hpp",
        "semantic_name": "任务模型头文件",
        "description": "定义 Task 类及其方法，包括构造函数、优先级获取和状态管理"
      },
      {
        "id": "Intermediate_scheduler_hpp",
        "parent_root": "Root_03",
        "file_path": "src/core/scheduler.hpp",
        "semantic_name": "调度器核心头文件",
        "description": "定义 Scheduler 类和模板类 Scheduler<T>，包含优先级计数和任务评估模板方法"
      }
    ],
    "leaf_nodes": [
      {
        "id": "Leaf_main",
        "parent_intermediate": "Intermediate_main_cpp",
        "ir_reference": "standalone_functions.main",
        "node_subtype": "standalone_function",
        "belongs_to_class": null,
        "semantic_name": "程序主函数",
        "description": "程序入口点，调用调度器的 evaluate 和 getHighPrioCount 方法"
      },
      {
        "id": "Leaf_Task_constructor",
        "parent_intermediate": "Intermediate_task_hpp",
        "ir_reference": "classes.Task.Task",
        "node_subtype": "member_function",
        "belongs_to_class": "models::Task",
        "semantic_name": "Task构造函数",
        "description": "初始化 Task 对象的 taskId 和 priority 成员"
      },
      {
        "id": "Leaf_Task_getPriority",
        "parent_intermediate": "Intermediate_task_hpp",
        "ir_reference": "classes.Task.getPriority",
        "node_subtype": "member_function",
        "belongs_to_class": "models::Task",
        "semantic_name": "获取任务优先级",
        "description": "返回任务的优先级值"
      },
      {
        "id": "Leaf_Task_activate",
        "parent_intermediate": "Intermediate_task_hpp",
        "ir_reference": "classes.Task.activate",
        "node_subtype": "member_function",
        "belongs_to_class": "models::Task",
        "semantic_name": "激活任务",
        "description": "将任务的 active 状态设置为 true"
      },
      {
        "id": "Leaf_Task_isActive",
        "parent_intermediate": "Intermediate_task_hpp",
        "ir_reference": "classes.Task.isActive",
        "node_subtype": "member_function",
        "belongs_to_class": "models::Task",
        "semantic_name": "检查任务激活状态",
        "description": "返回任务是否处于激活状态"
      },
      {
        "id": "Leaf_Scheduler_getHighPrioCount",
        "parent_intermediate": "Intermediate_scheduler_hpp",
        "ir_reference": "classes.Scheduler.getHighPrioCount",
        "node_subtype": "member_function",
        "belongs_to_class": "core::Scheduler",
        "semantic_name": "获取高优先级计数",
        "description": "返回调度器中高优先级任务的计数"
      },
      {
        "id": "Leaf_Scheduler_evaluate",
        "parent_intermediate": "Intermediate_scheduler_hpp",
        "ir_reference": "classes.Scheduler.evaluate",
        "node_subtype": "member_function",
        "belongs_to_class": "core::Scheduler<T>",
        "semantic_name": "评估任务",
        "description": "模板方法，评估任务并更新高优先级计数"
      }
    ]
  },
  "edges": {
    "inter_module_edges": [
      {
        "source": "Root_03",
        "target": "Root_01",
        "relation_type": "data_flow",
        "description": "主函数调用调度器的方法获取数据和执行任务评估",
        "evidence": "通过 main 函数的 control_flow.direct_calls 发现调用了 evaluate 和 getHighPrioCount 方法"
      },
      {
        "source": "Root_02",
        "target": "Root_03",
        "relation_type": "data_flow",
        "description": "调度器的 evaluate 模板方法依赖 Task 模型的方法进行任务评估",
        "evidence": "通过 evaluate 方法的 control_flow.direct_calls 发现调用了 activate 和 getPriority 方法，这些方法属于 Task 类"
      }
    ],
    "intra_module_edges": []
  }
}